bigquery_cleaner/__init__.py
bigquery_cleaner/bq_client.py
bigquery_cleaner/cli.py
bigquery_cleaner/config.py
bigquery_cleaner/core_operations.py
bigquery_cleaner/utils.py
bigquery_cleaner/queries/sql.py
bigquery_cleaner-0.1.3.dist-info/METADATA
bigquery_cleaner-0.1.3.dist-info/WHEEL
bigquery_cleaner-0.1.3.dist-info/entry_points.txt
bigquery_cleaner-0.1.3.dist-info/licenses/LICENSE
bigquery_cleaner-0.1.3.dist-info/RECORD
