Metadata-Version: 2.4
Name: bigquery-cleaner
Version: 0.1.3
Summary: CLI tool to clean up your BigQuery old and unused datasets and tables.
Author: Alan Vainsencher
License-Expression: MIT
License-File: LICENSE
Requires-Python: >=3.10
Requires-Dist: google-auth>=2.0
Requires-Dist: google-cloud-bigquery>=3.25
Requires-Dist: rich>=14.2.0
Requires-Dist: tomli>=2.0; python_version < '3.11'
Requires-Dist: typer>=0.12
